passprotecttxt/README.MD
passprotecttxt/__init__.py
passprotecttxt/requirements.txt
passprotecttxt/thirdparty.json
passprotecttxt-0.13.dist-info/LICENSE.rst
passprotecttxt-0.13.dist-info/METADATA
passprotecttxt-0.13.dist-info/WHEEL
passprotecttxt-0.13.dist-info/top_level.txt
passprotecttxt-0.13.dist-info/RECORD
