Metadata-Version: 2.1
Name: passprotecttxt
Version: 0.13
Summary: protects a text with a password
Home-page: https://github.com/hansalemaos/passprotecttxt
Author: Johannes Fischer
Author-email: aulasparticularesdealemaosp@gmail.com
License: MIT
Keywords: password,encrypt
Classifier: Development Status :: 4 - Beta
Classifier: Programming Language :: Python :: 3 :: Only
Classifier: Programming Language :: Python :: 3.10
Classifier: Topic :: Software Development :: Libraries :: Python Modules
Classifier: Topic :: Utilities
License-File: LICENSE.rst
Requires-Dist: LatinFixer
Requires-Dist: cryptography
